twitchy/__init__.py
twitchy/api.py
twitchy/base.py
twitchy/constants.py
twitchy/exceptions.py
twitchy/resources.py
twitchy/test.py
twitchy/utils.py
Twitchy-0.0.1.dist-info/AUTHORS.rst
Twitchy-0.0.1.dist-info/LICENSE.txt
Twitchy-0.0.1.dist-info/METADATA
Twitchy-0.0.1.dist-info/WHEEL
Twitchy-0.0.1.dist-info/top_level.txt
Twitchy-0.0.1.dist-info/RECORD
