Metadata-Version: 2.1
Name: Twitchy
Version: 0.0.1
Summary: Twitchy is an easy to use Twitch API wrapper with focus on the Helix API, webhooks, and chat.
Home-page: https://github.com/codespent/twitchy
Author: Patrick Hanford
Author-email: hanfordpatrick@gmail.com
License: mit
Platform: any
Classifier: Development Status :: 4 - Beta
Classifier: Programming Language :: Python
Provides-Extra: testing
Requires-Dist: pytest ; extra == 'testing'
Requires-Dist: pytest-cov ; extra == 'testing'
